invfinsdk/__init__.py
invfinsdk/__version__.py
invfinsdk/api.py
invfinsdk/client.py
invfinsdk/constants.py
invfinsdk-0.1.1.dist-info/AUTHORS.md
invfinsdk-0.1.1.dist-info/LICENSE
invfinsdk-0.1.1.dist-info/METADATA
invfinsdk-0.1.1.dist-info/WHEEL
invfinsdk-0.1.1.dist-info/top_level.txt
invfinsdk-0.1.1.dist-info/RECORD
