Metadata-Version: 2.1
Name: invfinsdk
Version: 0.1.1
Summary: An SDK to interact with InvFin endpoints
Home-page: https://github.com/InvFin/Python-sdk
Author: Lucas Montes
Author-email: lluc23@hotmail.com
License: MIT license
Keywords: invfinsdk
Classifier: Development Status :: 2 - Pre-Alpha
Classifier: Intended Audience :: Developers
Classifier: License :: OSI Approved :: MIT License
Classifier: Natural Language :: English
Classifier: Programming Language :: Python :: 3
Classifier: Programming Language :: Python :: 3.6
Classifier: Programming Language :: Python :: 3.7
Classifier: Programming Language :: Python :: 3.8
Requires-Python: >=3.6
License-File: LICENSE
License-File: AUTHORS.md
Requires-Dist: requests
